LICENSE
MANIFEST.in
README.md
requirements.txt
setup.py
mongo_inspector/__init__.py
mongo_inspector/mongo_inspector.py
mongo_inspector.egg-info/PKG-INFO
mongo_inspector.egg-info/SOURCES.txt
mongo_inspector.egg-info/dependency_links.txt
mongo_inspector.egg-info/requires.txt
mongo_inspector.egg-info/top_level.txt
mongo_inspector/js/map.js
mongo_inspector/js/reduce.js