Metadata-Version: 1.1
Name: mongo-inspector
Version: 0.1
Summary: Schema extractor for MongoDB.
Home-page: http://github.com/morphyn/mongo-inspector
Author: Martin Maillard
Author-email: self@martin-maillard.com
License: Copyright 2013 Martin Maillard
